QuickStart_Rhy/API/AITranslate.py
QuickStart_Rhy/API/AliCloud.py
QuickStart_Rhy/API/BaiduCloud.py
QuickStart_Rhy/API/DeepL.py
QuickStart_Rhy/API/DeepLX.py
QuickStart_Rhy/API/GPT/__init__.py
QuickStart_Rhy/API/GPT/alapi.py
QuickStart_Rhy/API/GPT/common.py
QuickStart_Rhy/API/GPT/openai.py
QuickStart_Rhy/API/GPT/poe.py
QuickStart_Rhy/API/Lolicon.py
QuickStart_Rhy/API/PushDeer.py
QuickStart_Rhy/API/QiniuOSS.py
QuickStart_Rhy/API/Serper.py
QuickStart_Rhy/API/SimpleAPI.py
QuickStart_Rhy/API/TencentCloud.py
QuickStart_Rhy/API/__init__.py
QuickStart_Rhy/API/alapi.py
QuickStart_Rhy/ImageTools/ColorTools.py
QuickStart_Rhy/ImageTools/ImagePreview.py
QuickStart_Rhy/ImageTools/ImageTools.py
QuickStart_Rhy/ImageTools/VideoTools.py
QuickStart_Rhy/ImageTools/__init__.py
QuickStart_Rhy/NetTools/HttpServer.py
QuickStart_Rhy/NetTools/M3u8DL.py
QuickStart_Rhy/NetTools/MultiSingleDL.py
QuickStart_Rhy/NetTools/NormalDL.py
QuickStart_Rhy/NetTools/WiFi.py
QuickStart_Rhy/NetTools/WiFiDarwin.py
QuickStart_Rhy/NetTools/__init__.py
QuickStart_Rhy/NumbaTools/__init__.py
QuickStart_Rhy/SystemTools/Compress.py
QuickStart_Rhy/SystemTools/Diff.py
QuickStart_Rhy/SystemTools/DiskMac.py
QuickStart_Rhy/SystemTools/FileHash.py
QuickStart_Rhy/SystemTools/__init__.py
QuickStart_Rhy/ThreadTools/__init__.py
QuickStart_Rhy/TuiTools/Bar.py
QuickStart_Rhy/TuiTools/Line.py
QuickStart_Rhy/TuiTools/Table.py
QuickStart_Rhy/TuiTools/__init__.py
QuickStart_Rhy/Wrapper/__init__.py
QuickStart_Rhy/__cache__.py
QuickStart_Rhy/__config__.py
QuickStart_Rhy/__init__.py
QuickStart_Rhy/apiTools.py
QuickStart_Rhy/funcList.py
QuickStart_Rhy/imageDeal.py
QuickStart_Rhy/lang.json
QuickStart_Rhy/main.py
QuickStart_Rhy/netTools.py
QuickStart_Rhy/qsLesson.py
QuickStart_Rhy/system.py
quickstart_rhy-0.7.49.dist-info/LICENSE
quickstart_rhy-0.7.49.dist-info/METADATA
quickstart_rhy-0.7.49.dist-info/WHEEL
quickstart_rhy-0.7.49.dist-info/entry_points.txt
quickstart_rhy-0.7.49.dist-info/RECORD
