Metadata-Version: 2.3
Name: QuickStart-Rhy
Version: 0.7.49
Summary: A Command Line Toolbox
License: MIT
Author: Rhythmicc
Author-email: rhythmlian.cn@gmail.com
Requires-Python: >=3.8,<4.0
Classifier: License :: OSI Approved :: MIT License
Classifier: Programming Language :: Python :: 3
Classifier: Programming Language :: Python :: 3.8
Classifier: Programming Language :: Python :: 3.9
Classifier: Programming Language :: Python :: 3.10
Classifier: Programming Language :: Python :: 3.11
Classifier: Programming Language :: Python :: 3.12
Classifier: Programming Language :: Python :: 3.13
Requires-Dist: Qpro (>=0.13.0,<0.14.0)
Requires-Dist: inquirer-rhy (>=0.1.2,<0.2.0)
Requires-Dist: requests (>=2.31.0,<3.0.0)
Requires-Dist: rich (>=13.3.4,<14.0.0)
Requires-Dist: urllib3 (>=1.26.15,<2.0.0)
